give_me_code.py
give_me_code-0.0.1.dist-info/top_level.txt
give_me_code-0.0.1.dist-info/METADATA
give_me_code-0.0.1.dist-info/DESCRIPTION.rst
give_me_code-0.0.1.dist-info/metadata.json
give_me_code-0.0.1.dist-info/WHEEL
give_me_code-0.0.1.dist-info/RECORD
