Metadata-Version: 2.0
Name: give-me-code
Version: 0.0.1
Summary: Return http response with any error code you want.
Home-page: https://github.com/winkidney/GiveMeCode
Author: winkidney
Author-email: winkidney@gmail.com
License: MIT
Platform: UNKNOWN
Requires-Dist: flask
